{"fmus":{"{sensor1}":"Sensor_Block_01.fmu","{sensor2}":"Sensor_Block_02.fmu","{controlAR}":"extended_robot.fmu"},"connections":{"{sensor1}.sensor1Instance.lf_1_sensor_reading":["{controlAR}.controlARInstance.lightSensors_left"],"{controlAR}.controlARInstance.xx":["{sensor1}.sensor1Instance.robot_x","{sensor2}.sensor2Instance.robot_x"],"{controlAR}.controlARInstance.yy":["{sensor1}.sensor1Instance.robot_y","{sensor2}.sensor2Instance.robot_y"],"{controlAR}.controlARInstance.theta":["{sensor1}.sensor1Instance.robot_theta","{sensor2}.sensor2Instance.robot_theta"],"{controlAR}.controlARInstance.motorSpeed_left":[],"{controlAR}.controlARInstance.motorSpeed_right":[],"{sensor2}.sensor2Instance.lf_1_sensor_reading":["{controlAR}.controlARInstance.lightSensors_right"]},"parameters":{"{sensor1}.sensor1Instance.lf_position_x":-0.01,"{sensor1}.sensor1Instance.lf_position_y":0.065,"{sensor2}.sensor2Instance.lf_position_x":0.01,"{sensor2}.sensor2Instance.lf_position_y":0.065}}